gpflow/__init__.py
gpflow/_settings.py
gpflow/_version.py
gpflow/conditionals.py
gpflow/densities.py
gpflow/ekernels.py
gpflow/gpflowrc
gpflow/gplvm.py
gpflow/gpmc.py
gpflow/gpr.py
gpflow/hmc.py
gpflow/kernels.py
gpflow/kullback_leiblers.py
gpflow/likelihoods.py
gpflow/mean_functions.py
gpflow/minibatch.py
gpflow/model.py
gpflow/param.py
gpflow/priors.py
gpflow/quadrature.py
gpflow/scoping.py
gpflow/session.py
gpflow/sgpmc.py
gpflow/sgpr.py
gpflow/svgp.py
gpflow/tf_hacks.py
gpflow/tf_wraps.py
gpflow/transforms.py
gpflow/vgp.py
gpflow_old-0.5.dist-info/LICENSE
gpflow_old-0.5.dist-info/METADATA
gpflow_old-0.5.dist-info/WHEEL
gpflow_old-0.5.dist-info/top_level.txt
gpflow_old-0.5.dist-info/RECORD
